{
  "configurations": [
    {
      "name": "x64-Debug",
      "generator": "Ninja",
      "configurationType": "Debug",
      "inheritEnvironments": [ "msvc_x64_x64" ],
      "buildRoot": "${projectDir}\\Builds\\ninja\\build\\${name}",
      "installRoot": "${projectDir}\\Builds\\ninja\\install\\${name}",
      "cmakeCommandArgs": "",
      "buildCommandArgs": "",
      "ctestCommandArgs": "",
      "variables": [
        {
          "name": "CMAKE_PREFIX_PATH",
          "value": "C:\\lib\\JUCEbuild",
          "type": "FILEPATH"
        }
      ]
    }
  ]
}